sinergym/__init__.py
sinergym/config/__init__.py
sinergym/config/modeling.py
sinergym/data/buildings/1ZoneDataCenterCRAC_wApproachTemp.epJSON
sinergym/data/buildings/2ZoneDataCenterHVAC_wEconomizer_CW.epJSON
sinergym/data/buildings/2ZoneDataCenterHVAC_wEconomizer_DX.epJSON
sinergym/data/buildings/5ZoneAutoDXVAV.epJSON
sinergym/data/buildings/ASHRAE901_OfficeMedium_STD2019_Denver.epJSON
sinergym/data/buildings/ASHRAE901_Warehouse_STD2019_Denver.epJSON
sinergym/data/buildings/LrgOff_GridStorageScheduled.epJSON
sinergym/data/buildings/ShopWithPVandBattery.epJSON
sinergym/data/buildings/radiant_residential_building.epJSON
sinergym/data/default_configuration/1ZoneDataCenterCRAC_wApproachTemp.yaml
sinergym/data/default_configuration/2ZoneDataCenterHVAC_wEconomizer_CW.yaml
sinergym/data/default_configuration/2ZoneDataCenterHVAC_wEconomizer_DX.yaml
sinergym/data/default_configuration/5ZoneAutoDXVAV.yaml
sinergym/data/default_configuration/ASHRAE901_OfficeMedium_STD2019_Denver.yaml
sinergym/data/default_configuration/ASHRAE901_Warehouse_STD2019_Denver.yaml
sinergym/data/default_configuration/LrgOff_GridStorageScheduled.yaml
sinergym/data/default_configuration/ShopWithPVandBattery.yaml
sinergym/data/default_configuration/radiant_residential_building.yaml
sinergym/data/energy_cost/PVPC_active_energy_billing_Iberian_Peninsula_2023.csv
sinergym/data/weather/AUS_NSW.Sydney.947670_IWEC.ddy
sinergym/data/weather/AUS_NSW.Sydney.947670_IWEC.epw
sinergym/data/weather/COL_Bogota.802220_IWEC.ddy
sinergym/data/weather/COL_Bogota.802220_IWEC.epw
sinergym/data/weather/ESP_Granada.084190_SWEC.ddy
sinergym/data/weather/ESP_Granada.084190_SWEC.epw
sinergym/data/weather/FIN_Helsinki.029740_IWEC.ddy
sinergym/data/weather/FIN_Helsinki.029740_IWEC.epw
sinergym/data/weather/JPN_Tokyo.Hyakuri.477150_IWEC.ddy
sinergym/data/weather/JPN_Tokyo.Hyakuri.477150_IWEC.epw
sinergym/data/weather/MDG_Antananarivo.670830_IWEC.ddy
sinergym/data/weather/MDG_Antananarivo.670830_IWEC.epw
sinergym-3.11.0.dist-info/METADATA
sinergym-3.11.0.dist-info/WHEEL
sinergym-3.11.0.dist-info/licenses/LICENSE
sinergym-3.11.0.dist-info/RECORD
