Metadata-Version: 2.4
Name: sinergym
Version: 3.11.0
Summary: Sinergym provides a Gymnasium-based interface to interact with building simulations. This allows control in simulation time through custom controllers, including reinforcement learning agents
License-Expression: MIT
License-File: LICENSE
Keywords: deep-reinforcement-learning,buildings,simulation,control,energy-optimization
Author: Alejandro Campoy Nieves
Author-email: alejandroac79@gmail.com
Maintainer: Alejandro Campoy Nieves
Maintainer-email: alejandroac79@gmail.com
Requires-Python: >=3.12
Classifier: Development Status :: 5 - Production/Stable
Classifier: Programming Language :: Python :: 3.12
Classifier: Operating System :: OS Independent
Provides-Extra: drl
Provides-Extra: extras
Provides-Extra: gcloud
Provides-Extra: notebooks
Provides-Extra: plots
Provides-Extra: test
Provides-Extra: wandb
Requires-Dist: IPython (>=9.4.0) ; extra == "extras"
Requires-Dist: IPython (>=9.4.0) ; extra == "notebooks"
Requires-Dist: coverage (>=7.10.4) ; extra == "extras"
Requires-Dist: coverage (>=7.10.4) ; extra == "test"
Requires-Dist: eppy (>=0.5.63)
Requires-Dist: epw (>=1.2.dev2)
Requires-Dist: google-api-python-client (>=2.179.0) ; extra == "extras"
Requires-Dist: google-api-python-client (>=2.179.0) ; extra == "gcloud"
Requires-Dist: google-cloud-storage (>=3.3.0) ; extra == "extras"
Requires-Dist: google-cloud-storage (>=3.3.0) ; extra == "gcloud"
Requires-Dist: gymnasium (>=1.2.0)
Requires-Dist: numpy (>=2.3.2)
Requires-Dist: oauth2client (>=4.1.3) ; extra == "extras"
Requires-Dist: oauth2client (>=4.1.3) ; extra == "gcloud"
Requires-Dist: pandas (>=2.3.1)
Requires-Dist: plotly (>=6.5.2) ; extra == "extras"
Requires-Dist: plotly (>=6.5.2) ; extra == "plots"
Requires-Dist: pytest (>=8.4.1) ; extra == "extras"
Requires-Dist: pytest (>=8.4.1) ; extra == "test"
Requires-Dist: pytest-cov (>=6.2.1) ; extra == "extras"
Requires-Dist: pytest-cov (>=6.2.1) ; extra == "test"
Requires-Dist: pytest-xdist (>=3.8.0) ; extra == "extras"
Requires-Dist: pytest-xdist (>=3.8.0) ; extra == "test"
Requires-Dist: pyyaml (>=6.0.2)
Requires-Dist: sb3-contrib (>=2.7.0) ; extra == "drl"
Requires-Dist: sb3-contrib (>=2.7.0) ; extra == "extras"
Requires-Dist: stable-baselines3 (>=2.7.0) ; extra == "drl"
Requires-Dist: stable-baselines3 (>=2.7.0) ; extra == "extras"
Requires-Dist: tqdm (>=4.67.1)
Requires-Dist: wandb (>=0.21.1) ; extra == "drl"
Requires-Dist: wandb (>=0.21.1) ; extra == "extras"
Requires-Dist: wandb (>=0.21.1) ; extra == "test"
Requires-Dist: wandb (>=0.21.1) ; extra == "wandb"
Requires-Dist: xlsxwriter (>=3.2.5)
Project-URL: Documentation, https://ugr-sail.github.io/sinergym
Project-URL: Homepage, https://github.com/ugr-sail/sinergym
Project-URL: Repository, https://github.com/ugr-sail/sinergym
